{
  "deparment": "NORTE DE SANTANDER",
  "cities": {
    "ABREGO": "ábrego_norsan",
    "ARBOLEDAS": "arboledas_norsan",
    "BOCHALEMA": "bochalema_norsan",
    "BUCARASICA": "bucarasica_norsan",
    "CACHIRA": "cáchira_norsan",
    "CACOTA": "cácota_norsan",
    "CHINACOTA": "chinácota_norsan",
    "CHITAGA": "chitagá_norsan",
    "CONVENCION": "convención_norsan",
    "CUCUTA": "cúcuta_norsan",
    "CUCUTILLA": "cucutilla_norsan",
    "DURANIA": "durania_norsan",
    "EL CARMEN": "elcarmen_norsan",
    "EL TARRA": "eltarra_norsan",
    "EL ZULIA": "elzulia_norsan",
    "GRAMALOTE": "gramalote_norsan",
    "HACARI": "hacarí_norsan",
    "HERRAN": "herrán_norsan",
    "LA ESPERANZA": "laesperanza_norsan",
    "LA PLAYA DE BELEN": "laplayadebelén_norsan",
    "LABATECA": "labateca_norsan",
    "LOS PATIOS": "lospatios_norsan",
    "LOURDES": "lourdes_norsan",
    "MUTISCUA": "mutiscua_norsan",
    "OCAÑA": "ocaña_norsan",
    "PAMPLONA": "pamplona_norsan",
    "PAMPLONITA": "pamplonita_norsan",
    "PUERTO SANTANDER": "puertosantander_norsan",
    "RAGONVALIA": "ragonvalia_norsan",
    "SALAZAR DE LAS PALMAS": "salazardelaspalmas_norsan",
    "SAN CALIXTO": "sancalixto_norsan",
    "SAN CAYETANO": "sancayetano_norsan",
    "SANTIAGO": "santiago_norsan",
    "SANTO DOMINGO DE SILOS": "santodomingodesilos_norsan",
    "SARDINATA": "sardinata_norsan",
    "TEORAMA": "teorama_norsan",
    "TIBU": "tibú_norsan",
    "TOLEDO": "toledo_norsan",
    "VILLA CARO": "villacaro_norsan",
    "VILLA DEL ROSARIO": "villadelrosario_norsan"
  }
}
